[
  {
    "nombre": "adri",
    "curso": "11",
    "materias": [
      {
        "materia": "1",
        "julio": "1",
        "agosto": "1",
        "noviembre": "1",
        "diciembre": "1"
      },
      {
        "materia": "1",
        "julio": "1",
        "agosto": "1",
        "noviembre": "1",
        "diciembre": "1"
      },
      {
        "materia": "1",
        "julio": "1",
        "agosto": "1",
        "noviembre": "1",
        "diciembre": "1"
      },
      {
        "materia": "1",
        "julio": "1",
        "agosto": "1",
        "noviembre": "1",
        "diciembre": "1"
      }
    ]
  }
]