[
  {
    "nombre": "juan perez",
    "curso": "1°1°",
    "fechaHora": "14-07-25 | 14:14",
    "materias": [
      {
        "materia": "",
        "julio": "1",
        "agosto": "1",
        "noviembre": "1",
        "diciembre": "1"
      },
      {
        "materia": "",
        "julio": "",
        "agosto": "",
        "noviembre": "",
        "diciembre": ""
      },
      {
        "materia": "",
        "julio": "",
        "agosto": "",
        "noviembre": "",
        "diciembre": ""
      },
      {
        "materia": "",
        "julio": "",
        "agosto": "",
        "noviembre": "",
        "diciembre": ""
      }
    ]
  },
  {
    "nombre": "3",
    "curso": "1°1°",
    "fechaHora": "14-07-25 | 14:22",
    "materias": [
      {
        "materia": "",
        "julio": "",
        "agosto": "",
        "noviembre": "",
        "diciembre": ""
      },
      {
        "materia": "",
        "julio": "",
        "agosto": "",
        "noviembre": "",
        "diciembre": ""
      },
      {
        "materia": "",
        "julio": "",
        "agosto": "",
        "noviembre": "",
        "diciembre": ""
      },
      {
        "materia": "",
        "julio": "",
        "agosto": "",
        "noviembre": "",
        "diciembre": ""
      }
    ]
  },
  {
    "nombre": "4",
    "curso": "1°1°",
    "fechaHora": "14-07-25 | 14:23",
    "materias": [
      {
        "materia": "",
        "julio": "",
        "agosto": "",
        "noviembre": "",
        "diciembre": ""
      },
      {
        "materia": "",
        "julio": "",
        "agosto": "",
        "noviembre": "",
        "diciembre": ""
      },
      {
        "materia": "",
        "julio": "",
        "agosto": "",
        "noviembre": "",
        "diciembre": ""
      },
      {
        "materia": "",
        "julio": "",
        "agosto": "",
        "noviembre": "",
        "diciembre": ""
      }
    ]
  },
  {
    "nombre": "33",
    "curso": "1°1°",
    "fechaHora": "14-07-25 | 14:32",
    "materias": [
      {
        "materia": "",
        "julio": "1",
        "agosto": "",
        "noviembre": "",
        "diciembre": ""
      },
      {
        "materia": "",
        "julio": "",
        "agosto": "",
        "noviembre": "",
        "diciembre": ""
      },
      {
        "materia": "",
        "julio": "",
        "agosto": "",
        "noviembre": "",
        "diciembre": ""
      },
      {
        "materia": "",
        "julio": "",
        "agosto": "",
        "noviembre": "",
        "diciembre": ""
      }
    ]
  }
]